calendar_sse_mcp/__init__.py
calendar_sse_mcp/__main__.py
calendar_sse_mcp/calendar_store.py
calendar_sse_mcp/date_utils.py
calendar_sse_mcp/launch_agent.py
calendar_sse_mcp/models.py
calendar_sse_mcp/server.py
calendar_sse_mcp-0.1.20.dist-info/licenses/LICENSE
calendar_sse_mcp-0.1.20.dist-info/METADATA
calendar_sse_mcp-0.1.20.dist-info/WHEEL
calendar_sse_mcp-0.1.20.dist-info/entry_points.txt
calendar_sse_mcp-0.1.20.dist-info/top_level.txt
calendar_sse_mcp-0.1.20.dist-info/RECORD
