Metadata-Version: 2.4
Name: calendar-sse-mcp
Version: 0.1.20
Summary: A Model Context Protocol server for macOS Calendar.app
Requires-Python: >=3.10
License-File: LICENSE
Requires-Dist: mcp>=1.7.1
Requires-Dist: starlette>=0.46.2
Requires-Dist: python-dotenv>=1.0.0
Requires-Dist: pyobjc-framework-EventKit>=9.0
Requires-Dist: pyobjc-core>=9.0
Requires-Dist: pyobjc-framework-Cocoa>=9.0
Requires-Dist: requests>=2.32.3
Requires-Dist: sseclient-py>=1.8.0
Requires-Dist: pydantic>=2.0.0
Requires-Dist: dateparser>=1.2.0
Dynamic: license-file
